[
  {
    "line": 2,
    "elements": [
      {
        "before": [
          {
            "result": {
              "duration": 5239927262,
              "status": "passed"
            },
            "match": {
              "location": "Hook.setUp()"
            }
          }
        ],
        "line": 5,
        "name": "Google Search 2",
        "description": "",
        "id": ";google-search-2",
        "after": [
          {
            "result": {
              "duration": 690359895,
              "status": "passed"
            },
            "match": {
              "location": "Hook.tearDown()"
            }
          }
        ],
        "type": "scenario",
        "keyword": "Scenario",
        "steps": [
          {
            "result": {
              "duration": 104263799,
              "status": "passed"
            },
            "line": 6,
            "name": "I open a browser",
            "match": {
              "location": "GoogleSearch.i_open_a_browser()"
            },
            "keyword": "Given "
          },
          {
            "result": {
              "duration": 1136822638,
              "status": "passed"
            },
            "line": 7,
            "name": "I navigate to google page",
            "match": {
              "location": "GoogleSearch.i_navigate_to_google_page()"
            },
            "keyword": "When "
          },
          {
            "result": {
              "duration": 115763039,
              "status": "passed"
            },
            "line": 8,
            "name": "I validate the search tesxt field",
            "match": {
              "location": "GoogleSearch.i_validate_the_search_tesxt_field()"
            },
            "keyword": "Then "
          }
        ],
        "tags": [
          {
            "line": 4,
            "name": "@TSTINSC-8"
          }
        ]
      }
    ],
    "name": "",
    "description": "",
    "id": "",
    "keyword": "Feature",
    "uri": "GoogleSearch.feature",
    "tags": [
      {
        "line": 1,
        "name": "@TSTINSC-6"
      }
    ]
  }
]